[
    {
        "__typename": "GraphImage",
        "comments_disabled": false,
        "dimensions": {
            "height": 1080,
            "width": 1080
        },
        "display_url": "https://scontent-ort2-1.cdninstagram.com/vp/5af3b4c5b035bf28bdd3c5baa96d0a35/5AE2E2EC/t51.2885-15/e35/26185092_338313933312961_3612558195949568000_n.jpg",
        "edge_media_preview_like": {
            "count": 87
        },
        "edge_media_to_caption": {
            "edges": [
                {
                    "node": {
                        "text": "In progress piece... another snake will be added to the other side of the client’s neck as well as some rendering in the head of the 🐍..... tattoo by @louisbarak #tattoo #tattoos #tattooartist #chicagoartist #chicagotattooartist #chicagotattoo #blackworktattoo #blackandgrey #abstracttattoo \nThanks for looking 🙂"
                    }
                }
            ]
        },
        "edge_media_to_comment": {
            "count": 2
        },
        "id": "1690345864457155775",
        "is_video": false,
        "location": null,
        "owner": {
            "id": "51495250"
        },
        "shortcode": "Bd1UJuehPS_",
        "tags": [
            "tattooartist",
            "tattoos",
            "chicagotattooartist",
            "chicagoartist",
            "chicagotattoo",
            "blackandgrey",
            "abstracttattoo",
            "blackworktattoo",
            "tattoo"
        ],
        "taken_at_timestamp": 1515724951,
        "thumbnail_resources": [
            {
                "config_height": 150,
                "config_width": 150,
                "src": "https://scontent-ort2-1.cdninstagram.com/vp/162f38efebfd0968649700f90f2dd902/5ADAC389/t51.2885-15/s150x150/e35/26185092_338313933312961_3612558195949568000_n.jpg"
            },
            {
                "config_height": 240,
                "config_width": 240,
                "src": "https://scontent-ort2-1.cdninstagram.com/vp/47668ba8e6e49242093e1e1fdf278287/5AF4E3B6/t51.2885-15/s240x240/e35/26185092_338313933312961_3612558195949568000_n.jpg"
            },
            {
                "config_height": 320,
                "config_width": 320,
                "src": "https://scontent-ort2-1.cdninstagram.com/vp/e9ec6c0008bf9782331c1d135cd57251/5AE7A5CE/t51.2885-15/s320x320/e35/26185092_338313933312961_3612558195949568000_n.jpg"
            },
            {
                "config_height": 480,
                "config_width": 480,
                "src": "https://scontent-ort2-1.cdninstagram.com/vp/e508ccc28bbd48d3614c2633fba0b739/5AD95A48/t51.2885-15/s480x480/e35/26185092_338313933312961_3612558195949568000_n.jpg"
            },
            {
                "config_height": 640,
                "config_width": 640,
                "src": "https://scontent-ort2-1.cdninstagram.com/vp/d0fcd77ef35872b4aaa2f3f537b4f8aa/5AE3308D/t51.2885-15/s640x640/sh0.08/e35/26185092_338313933312961_3612558195949568000_n.jpg"
            }
        ],
        "thumbnail_src": "https://scontent-ort2-1.cdninstagram.com/vp/d0fcd77ef35872b4aaa2f3f537b4f8aa/5AE3308D/t51.2885-15/s640x640/sh0.08/e35/26185092_338313933312961_3612558195949568000_n.jpg",
        "urls": [
            "https://scontent-ort2-1.cdninstagram.com/vp/5af3b4c5b035bf28bdd3c5baa96d0a35/5AE2E2EC/t51.2885-15/e35/26185092_338313933312961_3612558195949568000_n.jpg"
        ]
    },
    {
        "__typename": "GraphImage",
        "comments_disabled": false,
        "dimensions": {
            "height": 1119,
            "width": 1080
        },
        "display_url": "https://scontent-ort2-1.cdninstagram.com/vp/78deb1ec0909af40f4d250bf3697818a/5AF9D6C1/t51.2885-15/e35/25038427_158966771402999_7539021455481110528_n.jpg",
        "edge_media_preview_like": {
            "count": 35
        },
        "edge_media_to_caption": {
            "edges": [
                {
                    "node": {
                        "text": "Victorian lady done by @bobbyearly .\n.\n#victorian #portrait #portraittattoo #blackandgray #tattoo #chicago #chicagotattoo #revolutiontattoo #chicagotattooartist #bobbyearly"
                    }
                }
            ]
        },
        "edge_media_to_comment": {
            "count": 1
        },
        "id": "1686457321292872717",
        "is_video": false,
        "location": {
            "has_public_page": true,
            "id": "60963",
            "name": "The Empty Bottle",
            "slug": "the-empty-bottle"
        },
        "owner": {
            "id": "51495250"
        },
        "shortcode": "Bdnf_-chLwN",
        "tags": [
            "blackandgray",
            "victorian",
            "chicago",
            "chicagotattooartist",
            "chicagotattoo",
            "portraittattoo",
            "bobbyearly",
            "portrait",
            "revolutiontattoo",
            "tattoo"
        ],
        "taken_at_timestamp": 1515261400,
        "thumbnail_resources": [
            {
                "config_height": 150,
                "config_width": 150,
                "src": "https://scontent-ort2-1.cdninstagram.com/vp/fe7a469f139009b50e714d118bfae1b4/5AECDD64/t51.2885-15/s150x150/e35/c0.19.1080.1080/25038427_158966771402999_7539021455481110528_n.jpg"
            },
            {
                "config_height": 240,
                "config_width": 240,
                "src": "https://scontent-ort2-1.cdninstagram.com/vp/ed1a58d562e482448c23a18ca7e967f7/5AF219F2/t51.2885-15/s240x240/e35/c0.19.1080.1080/25038427_158966771402999_7539021455481110528_n.jpg"
            },
            {
                "config_height": 320,
                "config_width": 320,
                "src": "https://scontent-ort2-1.cdninstagram.com/vp/e0a912b708fc00e5ccda6e3392a2f602/5AE8ACF4/t51.2885-15/s320x320/e35/c0.19.1080.1080/25038427_158966771402999_7539021455481110528_n.jpg"
            },
            {
                "config_height": 480,
                "config_width": 480,
                "src": "https://scontent-ort2-1.cdninstagram.com/vp/44aa901c0fffaded20b8b4bfd65f0efc/5ADC5347/t51.2885-15/s480x480/e35/c0.19.1080.1080/25038427_158966771402999_7539021455481110528_n.jpg"
            },
            {
                "config_height": 640,
                "config_width": 640,
                "src": "https://scontent-ort2-1.cdninstagram.com/vp/72c18039ff0012aea44fe118d128bc90/5AF253F0/t51.2885-15/s640x640/sh0.08/e35/c0.19.1080.1080/25038427_158966771402999_7539021455481110528_n.jpg"
            }
        ],
        "thumbnail_src": "https://scontent-ort2-1.cdninstagram.com/vp/72c18039ff0012aea44fe118d128bc90/5AF253F0/t51.2885-15/s640x640/sh0.08/e35/c0.19.1080.1080/25038427_158966771402999_7539021455481110528_n.jpg",
        "urls": [
            "https://scontent-ort2-1.cdninstagram.com/vp/78deb1ec0909af40f4d250bf3697818a/5AF9D6C1/t51.2885-15/e35/25038427_158966771402999_7539021455481110528_n.jpg"
        ]
    },
    {
        "__typename": "GraphImage",
        "comments_disabled": false,
        "dimensions": {
            "height": 565,
            "width": 1080
        },
        "display_url": "https://scontent-ort2-1.cdninstagram.com/vp/45cf4ff896a6fb8031d3d36439923923/5ADCD271/t51.2885-15/e35/26072871_521390734899537_717062090195468288_n.jpg",
        "edge_media_preview_like": {
            "count": 44
        },
        "edge_media_to_caption": {
            "edges": [
                {
                    "node": {
                        "text": "Lettering by @bobbyearly done today. Walk ins of all kinds are welcome! #revolutiontattoo #revolutiontattoochicago #chicagotattooshops #chicagotattooartist #letteringtattoos #blackworktattoos #calligraphy"
                    }
                }
            ]
        },
        "edge_media_to_comment": {
            "count": 0
        },
        "id": "1686100095885749396",
        "is_video": false,
        "location": {
            "has_public_page": true,
            "id": "204517928",
            "name": "Chicago, Illinois",
            "slug": "chicago-illinois"
        },
        "owner": {
            "id": "51495250"
        },
        "shortcode": "BdmOxqXBayU",
        "tags": [
            "revolutiontattoochicago",
            "chicagotattooartist",
            "blackworktattoos",
            "letteringtattoos",
            "chicagotattooshops",
            "calligraphy",
            "revolutiontattoo"
        ],
        "taken_at_timestamp": 1515218816,
        "thumbnail_resources": [
            {
                "config_height": 150,
                "config_width": 150,
                "src": "https://scontent-ort2-1.cdninstagram.com/vp/56347197120fcc196553b5f65cdc92ac/5AF27E69/t51.2885-15/s150x150/e35/c257.0.565.565/26072871_521390734899537_717062090195468288_n.jpg"
            },
            {
                "config_height": 240,
                "config_width": 240,
                "src": "https://scontent-ort2-1.cdninstagram.com/vp/27fe0988b2aeeca847d8b3b784a67d21/5AE1CDE2/t51.2885-15/s240x240/e35/c257.0.565.565/26072871_521390734899537_717062090195468288_n.jpg"
            },
            {
                "config_height": 320,
                "config_width": 320,
                "src": "https://scontent-ort2-1.cdninstagram.com/vp/369156b2b79612efa73fc2f3c26e2615/5AEB8476/t51.2885-15/s320x320/e35/c257.0.565.565/26072871_521390734899537_717062090195468288_n.jpg"
            },
            {
                "config_height": 480,
                "config_width": 480,
                "src": "https://scontent-ort2-1.cdninstagram.com/vp/bc0213a661047b6a7063f16970b20a29/5AEAA523/t51.2885-15/s480x480/e35/c257.0.565.565/26072871_521390734899537_717062090195468288_n.jpg"
            },
            {
                "config_height": 640,
                "config_width": 640,
                "src": "https://scontent-ort2-1.cdninstagram.com/vp/76cf5f01f0d17e3d9d0dcd64c3e32b10/5ADD316D/t51.2885-15/e35/c257.0.565.565/26072871_521390734899537_717062090195468288_n.jpg"
            }
        ],
        "thumbnail_src": "https://scontent-ort2-1.cdninstagram.com/vp/76cf5f01f0d17e3d9d0dcd64c3e32b10/5ADD316D/t51.2885-15/e35/c257.0.565.565/26072871_521390734899537_717062090195468288_n.jpg",
        "urls": [
            "https://scontent-ort2-1.cdninstagram.com/vp/45cf4ff896a6fb8031d3d36439923923/5ADCD271/t51.2885-15/e35/26072871_521390734899537_717062090195468288_n.jpg"
        ]
    },
    {
        "__typename": "GraphSidecar",
        "comments_disabled": false,
        "dimensions": {
            "height": 1079,
            "width": 1080
        },
        "display_url": "https://scontent-ort2-1.cdninstagram.com/vp/e9b25a112a4a2021729409145602b9fa/5AFA698E/t51.2885-15/e35/25023178_1569158659806702_8593704765832036352_n.jpg",
        "edge_media_preview_like": {
            "count": 50
        },
        "edge_media_to_caption": {
            "edges": [
                {
                    "node": {
                        "text": "Hey all! We would like to introduce you to the newest addition to the Revolution Tattoo family, Louis Barak. A Chicago native who does sweet black & grey, color surrealism, and graffiti inspired jamz! He will be at the shop today and every Sunday (among other days) for all of your tattoo needs. Give him a follow at @louisbarak and check him out, then stop on by and say hi! Happy New Year! #revolutiontattoo #revolutiontattoochicago #chicagotattooshops #chicagotattooartist #sweettatts"
                    }
                }
            ]
        },
        "edge_media_to_comment": {
            "count": 0
        },
        "id": "1682164748298672870",
        "is_video": false,
        "location": {
            "has_public_page": true,
            "id": "255100154",
            "name": "Chicago metropolitan area",
            "slug": "chicago-metropolitan-area"
        },
        "owner": {
            "id": "51495250"
        },
        "shortcode": "BdYP-0UBtrm",
        "tags": [
            "revolutiontattoochicago",
            "sweettatts",
            "chicagotattooartist",
            "chicagotattooshops",
            "revolutiontattoo"
        ],
        "taken_at_timestamp": 1514749686,
        "thumbnail_resources": [
            {
                "config_height": 150,
                "config_width": 150,
                "src": "https://scontent-ort2-1.cdninstagram.com/vp/e1f7dcb2c75ba487d560c5e2b702773e/5AF347D1/t51.2885-15/s150x150/e35/c0.0.1079.1079/25023178_1569158659806702_8593704765832036352_n.jpg"
            },
            {
                "config_height": 240,
                "config_width": 240,
                "src": "https://scontent-ort2-1.cdninstagram.com/vp/06cfc42cc63127e5f03593f8b0c18c88/5ADAB147/t51.2885-15/s240x240/e35/c0.0.1079.1079/25023178_1569158659806702_8593704765832036352_n.jpg"
            },
            {
                "config_height": 320,
                "config_width": 320,
                "src": "https://scontent-ort2-1.cdninstagram.com/vp/f3132689adda3e7c0dc82759fbaf383a/5AE74541/t51.2885-15/s320x320/e35/c0.0.1079.1079/25023178_1569158659806702_8593704765832036352_n.jpg"
            },
            {
                "config_height": 480,
                "config_width": 480,
                "src": "https://scontent-ort2-1.cdninstagram.com/vp/615bb22467ed1eee6eda9f97bc224e8e/5AF66EF2/t51.2885-15/s480x480/e35/c0.0.1079.1079/25023178_1569158659806702_8593704765832036352_n.jpg"
            },
            {
                "config_height": 640,
                "config_width": 640,
                "src": "https://scontent-ort2-1.cdninstagram.com/vp/c7154780ec9366a5f52976127d6df8b7/5ADA7B45/t51.2885-15/s640x640/sh0.08/e35/c0.0.1079.1079/25023178_1569158659806702_8593704765832036352_n.jpg"
            }
        ],
        "thumbnail_src": "https://scontent-ort2-1.cdninstagram.com/vp/c7154780ec9366a5f52976127d6df8b7/5ADA7B45/t51.2885-15/s640x640/sh0.08/e35/c0.0.1079.1079/25023178_1569158659806702_8593704765832036352_n.jpg",
        "urls": [
            "https://scontent-ort2-1.cdninstagram.com/vp/e9b25a112a4a2021729409145602b9fa/5AFA698E/t51.2885-15/e35/25023178_1569158659806702_8593704765832036352_n.jpg",
            "https://scontent-ort2-1.cdninstagram.com/vp/6e2c0a9056f94415bd4d23d297eb47e8/5AFC5421/t51.2885-15/e35/26155940_207581586477596_5369694011835547648_n.jpg",
            "https://scontent-ort2-1.cdninstagram.com/vp/3f7faba62771f1294131c57c20ac7711/5AF66FFF/t51.2885-15/e35/26069011_534827756878984_8883402341466767360_n.jpg",
            "https://scontent-ort2-1.cdninstagram.com/vp/02b87352d93a4f3efbde997cfe21b628/5AD871DC/t51.2885-15/e35/25024019_360746894397552_8926845385909993472_n.jpg"
        ]
    },
    {
        "__typename": "GraphImage",
        "comments_disabled": false,
        "dimensions": {
            "height": 1174,
            "width": 1080
        },
        "display_url": "https://scontent-ort2-1.cdninstagram.com/vp/ccce2720e8a5815cafa10c2b5f6307de/5AEDD6EB/t51.2885-15/e35/25038284_153435368632142_6445491987003998208_n.jpg",
        "edge_media_preview_like": {
            "count": 40
        },
        "edge_media_to_caption": {
            "edges": [
                {
                    "node": {
                        "text": "Hot Stuff devil/angel battle done by oms @witchbanger at @revolutiontattoo\n.\n.\n.\n.\n.\n.\n#revolutiontattoo #revolutiontattoochicago #chicagotattooartist #chicagotattooshops #tattoosbyoms #traditionaltattoos #hotstufftattoo"
                    }
                }
            ]
        },
        "edge_media_to_comment": {
            "count": 1
        },
        "id": "1678823259732531816",
        "is_video": false,
        "location": {
            "has_public_page": true,
            "id": "251042043",
            "name": "反.刺青・畫廊 Revolution Tattoo & Gallery",
            "slug": "revolution-tattoo-gallery"
        },
        "owner": {
            "id": "51495250"
        },
        "shortcode": "BdMYNwlBVpo",
        "tags": [
            "revolutiontattoochicago",
            "chicagotattooartist",
            "hotstufftattoo",
            "tattoosbyoms",
            "chicagotattooshops",
            "traditionaltattoos",
            "revolutiontattoo"
        ],
        "taken_at_timestamp": 1514351349,
        "thumbnail_resources": [
            {
                "config_height": 150,
                "config_width": 150,
                "src": "https://scontent-ort2-1.cdninstagram.com/vp/b0920f64fbbfc0abcae2523171caa51e/5AF49046/t51.2885-15/s150x150/e35/c0.47.1080.1080/25038284_153435368632142_6445491987003998208_n.jpg"
            },
            {
                "config_height": 240,
                "config_width": 240,
                "src": "https://scontent-ort2-1.cdninstagram.com/vp/ef119257ac9fe6ae5e438ab28f26976a/5AF6B1D0/t51.2885-15/s240x240/e35/c0.47.1080.1080/25038284_153435368632142_6445491987003998208_n.jpg"
            },
            {
                "config_height": 320,
                "config_width": 320,
                "src": "https://scontent-ort2-1.cdninstagram.com/vp/57d516646096385ecf89a772fbccc0ae/5AEDF0D6/t51.2885-15/s320x320/e35/c0.47.1080.1080/25038284_153435368632142_6445491987003998208_n.jpg"
            },
            {
                "config_height": 480,
                "config_width": 480,
                "src": "https://scontent-ort2-1.cdninstagram.com/vp/948ae96e3f975aad5757394cfa562e54/5AE82565/t51.2885-15/s480x480/e35/c0.47.1080.1080/25038284_153435368632142_6445491987003998208_n.jpg"
            },
            {
                "config_height": 640,
                "config_width": 640,
                "src": "https://scontent-ort2-1.cdninstagram.com/vp/4be9be6e5acfa9a93ddf804e5ea410f2/5AF035D2/t51.2885-15/s640x640/sh0.08/e35/c0.47.1080.1080/25038284_153435368632142_6445491987003998208_n.jpg"
            }
        ],
        "thumbnail_src": "https://scontent-ort2-1.cdninstagram.com/vp/4be9be6e5acfa9a93ddf804e5ea410f2/5AF035D2/t51.2885-15/s640x640/sh0.08/e35/c0.47.1080.1080/25038284_153435368632142_6445491987003998208_n.jpg",
        "urls": [
            "https://scontent-ort2-1.cdninstagram.com/vp/ccce2720e8a5815cafa10c2b5f6307de/5AEDD6EB/t51.2885-15/e35/25038284_153435368632142_6445491987003998208_n.jpg"
        ]
    },
    {
        "__typename": "GraphSidecar",
        "comments_disabled": false,
        "dimensions": {
            "height": 750,
            "width": 750
        },
        "display_url": "https://scontent-ort2-1.cdninstagram.com/vp/6ed5ed5169805ff8fbac59247778bdec/5AF10B8C/t51.2885-15/e35/25017894_376151192836587_2730399267997876224_n.jpg",
        "edge_media_preview_like": {
            "count": 149
        },
        "edge_media_to_caption": {
            "edges": [
                {
                    "node": {
                        "text": "Happy Holidaze from the @revolutiontattoo @sideshowgallerychicago crew."
                    }
                }
            ]
        },
        "edge_media_to_comment": {
            "count": 7
        },
        "id": "1674234864314226938",
        "is_video": false,
        "location": {
            "has_public_page": true,
            "id": "855955803",
            "name": "Duck Duck Goat",
            "slug": "duck-duck-goat"
        },
        "owner": {
            "id": "51495250"
        },
        "shortcode": "Bc8E70WBhj6",
        "tags": [],
        "taken_at_timestamp": 1513804370,
        "thumbnail_resources": [
            {
                "config_height": 150,
                "config_width": 150,
                "src": "https://scontent-ort2-1.cdninstagram.com/vp/e79d3011025089a9bf4768e9ce6f0075/5AD9E6E9/t51.2885-15/s150x150/e35/25017894_376151192836587_2730399267997876224_n.jpg"
            },
            {
                "config_height": 240,
                "config_width": 240,
                "src": "https://scontent-ort2-1.cdninstagram.com/vp/c18d43fb4f47a3c65e0c5c61c664920a/5ADED1D6/t51.2885-15/s240x240/e35/25017894_376151192836587_2730399267997876224_n.jpg"
            },
            {
                "config_height": 320,
                "config_width": 320,
                "src": "https://scontent-ort2-1.cdninstagram.com/vp/1fed972570f7babc956b91ded8304000/5AFF17AE/t51.2885-15/s320x320/e35/25017894_376151192836587_2730399267997876224_n.jpg"
            },
            {
                "config_height": 480,
                "config_width": 480,
                "src": "https://scontent-ort2-1.cdninstagram.com/vp/7422fb51b4670198eec13d9c4ed37808/5ADC5928/t51.2885-15/s480x480/e35/25017894_376151192836587_2730399267997876224_n.jpg"
            },
            {
                "config_height": 640,
                "config_width": 640,
                "src": "https://scontent-ort2-1.cdninstagram.com/vp/1022b072b6ce5b8fc43ada91b89bd162/5AE027ED/t51.2885-15/s640x640/sh0.08/e35/25017894_376151192836587_2730399267997876224_n.jpg"
            }
        ],
        "thumbnail_src": "https://scontent-ort2-1.cdninstagram.com/vp/1022b072b6ce5b8fc43ada91b89bd162/5AE027ED/t51.2885-15/s640x640/sh0.08/e35/25017894_376151192836587_2730399267997876224_n.jpg",
        "urls": [
            "https://scontent-ort2-1.cdninstagram.com/vp/6ed5ed5169805ff8fbac59247778bdec/5AF10B8C/t51.2885-15/e35/25017894_376151192836587_2730399267997876224_n.jpg",
            "https://scontent-ort2-1.cdninstagram.com/vp/8e24317c5779da2b6b954f96be6f53f0/5ADE75F7/t51.2885-15/e35/25016404_1517009765044332_3121188906217766912_n.jpg",
            "https://scontent-ort2-1.cdninstagram.com/vp/2f2e10472f55fb77008835991a554177/5AF07F0A/t51.2885-15/e35/24838290_336404813502379_8365095540840464384_n.jpg",
            "https://scontent-ort2-1.cdninstagram.com/vp/85aa625dfeca8c7ad101c09b83b74ef4/5AFB4A8F/t51.2885-15/e35/25016656_331681307310369_8530471667435044864_n.jpg",
            "https://scontent-ort2-1.cdninstagram.com/vp/cda116af86142ce9a907ddd92b0610e5/5ADD8A0E/t51.2885-15/e35/25017848_307967176389515_5321785833492054016_n.jpg",
            "https://scontent-ort2-1.cdninstagram.com/vp/078b562466cfa73306c704a590f5be47/5AF25AB1/t51.2885-15/e35/25026227_156793301608763_3840787543968710656_n.jpg"
        ]
    },
    {
        "__typename": "GraphImage",
        "comments_disabled": false,
        "dimensions": {
            "height": 1080,
            "width": 1080
        },
        "display_url": "https://scontent-ort2-1.cdninstagram.com/vp/059a386a66dd97b051b282b512e0a71d/5AEF0D7C/t51.2885-15/e35/25011587_357037164761003_4221945803926667264_n.jpg",
        "edge_media_preview_like": {
            "count": 38
        },
        "edge_media_to_caption": {
            "edges": [
                {
                    "node": {
                        "text": "We will be closing at 7pm for the @sideshowgallerychicago @revolutiontattoo holiday party. Cheers"
                    }
                }
            ]
        },
        "edge_media_to_comment": {
            "count": 0
        },
        "id": "1673554510741841397",
        "is_video": false,
        "location": null,
        "owner": {
            "id": "51495250"
        },
        "shortcode": "Bc5qPXtBSX1",
        "tags": [],
        "taken_at_timestamp": 1513723265,
        "thumbnail_resources": [
            {
                "config_height": 150,
                "config_width": 150,
                "src": "https://scontent-ort2-1.cdninstagram.com/vp/0fd523140a84541992e1c56f5e6c7bbd/5AEA8119/t51.2885-15/s150x150/e35/25011587_357037164761003_4221945803926667264_n.jpg"
            },
            {
                "config_height": 240,
                "config_width": 240,
                "src": "https://scontent-ort2-1.cdninstagram.com/vp/dcf5ca799bb7cceab058560c0eb36164/5AE24B26/t51.2885-15/s240x240/e35/25011587_357037164761003_4221945803926667264_n.jpg"
            },
            {
                "config_height": 320,
                "config_width": 320,
                "src": "https://scontent-ort2-1.cdninstagram.com/vp/200265a256650b889ca6e5831957c284/5AF5C15E/t51.2885-15/s320x320/e35/25011587_357037164761003_4221945803926667264_n.jpg"
            },
            {
                "config_height": 480,
                "config_width": 480,
                "src": "https://scontent-ort2-1.cdninstagram.com/vp/2b314681b980fd7aa9ac756fb67f2cb2/5ADE99D8/t51.2885-15/s480x480/e35/25011587_357037164761003_4221945803926667264_n.jpg"
            },
            {
                "config_height": 640,
                "config_width": 640,
                "src": "https://scontent-ort2-1.cdninstagram.com/vp/dbb13f58acd3dc65a76f71b13c409694/5ADC711D/t51.2885-15/s640x640/sh0.08/e35/25011587_357037164761003_4221945803926667264_n.jpg"
            }
        ],
        "thumbnail_src": "https://scontent-ort2-1.cdninstagram.com/vp/dbb13f58acd3dc65a76f71b13c409694/5ADC711D/t51.2885-15/s640x640/sh0.08/e35/25011587_357037164761003_4221945803926667264_n.jpg",
        "urls": [
            "https://scontent-ort2-1.cdninstagram.com/vp/059a386a66dd97b051b282b512e0a71d/5AEF0D7C/t51.2885-15/e35/25011587_357037164761003_4221945803926667264_n.jpg"
        ]
    },
    {
        "__typename": "GraphImage",
        "comments_disabled": false,
        "dimensions": {
            "height": 1080,
            "width": 1080
        },
        "display_url": "https://scontent-ort2-1.cdninstagram.com/vp/8a19ca3cc94b76438605cde757e60bb5/5AF6E356/t51.2885-15/e35/24331580_133173664045884_5353534386362908672_n.jpg",
        "edge_media_preview_like": {
            "count": 41
        },
        "edge_media_to_caption": {
            "edges": [
                {
                    "node": {
                        "text": "Robin by @bobbyearly .\n.\n#birdtattoo #robin #tattoo #chicago #chicagotattoo #revolutiontattoo #chicagotattooartist #bobbyearly"
                    }
                }
            ]
        },
        "edge_media_to_comment": {
            "count": 0
        },
        "id": "1673430934265021963",
        "is_video": false,
        "location": {
            "has_public_page": true,
            "id": "122322558",
            "name": "Concord Music Hall",
            "slug": "concord-music-hall"
        },
        "owner": {
            "id": "51495250"
        },
        "shortcode": "Bc5OJGJBEYL",
        "tags": [
            "tattoo",
            "chicago",
            "chicagotattooartist",
            "robin",
            "birdtattoo",
            "bobbyearly",
            "revolutiontattoo",
            "chicagotattoo"
        ],
        "taken_at_timestamp": 1513708534,
        "thumbnail_resources": [
            {
                "config_height": 150,
                "config_width": 150,
                "src": "https://scontent-ort2-1.cdninstagram.com/vp/4d282c6b40fcca440541ad7339937928/5AE86233/t51.2885-15/s150x150/e35/24331580_133173664045884_5353534386362908672_n.jpg"
            },
            {
                "config_height": 240,
                "config_width": 240,
                "src": "https://scontent-ort2-1.cdninstagram.com/vp/7b6ec31336d834ab684aa94d9b54d708/5AE7B60C/t51.2885-15/s240x240/e35/24331580_133173664045884_5353534386362908672_n.jpg"
            },
            {
                "config_height": 320,
                "config_width": 320,
                "src": "https://scontent-ort2-1.cdninstagram.com/vp/2d149d247712898ae66e330710e27954/5AE9B274/t51.2885-15/s320x320/e35/24331580_133173664045884_5353534386362908672_n.jpg"
            },
            {
                "config_height": 480,
                "config_width": 480,
                "src": "https://scontent-ort2-1.cdninstagram.com/vp/493b8fb7f91fd1532d6a01287c5facf7/5AE5DAF2/t51.2885-15/s480x480/e35/24331580_133173664045884_5353534386362908672_n.jpg"
            },
            {
                "config_height": 640,
                "config_width": 640,
                "src": "https://scontent-ort2-1.cdninstagram.com/vp/b814001b97522b99307a0fd7fedde3df/5AF5BA37/t51.2885-15/s640x640/sh0.08/e35/24331580_133173664045884_5353534386362908672_n.jpg"
            }
        ],
        "thumbnail_src": "https://scontent-ort2-1.cdninstagram.com/vp/b814001b97522b99307a0fd7fedde3df/5AF5BA37/t51.2885-15/s640x640/sh0.08/e35/24331580_133173664045884_5353534386362908672_n.jpg",
        "urls": [
            "https://scontent-ort2-1.cdninstagram.com/vp/8a19ca3cc94b76438605cde757e60bb5/5AF6E356/t51.2885-15/e35/24331580_133173664045884_5353534386362908672_n.jpg"
        ]
    },
    {
        "__typename": "GraphImage",
        "comments_disabled": false,
        "dimensions": {
            "height": 1080,
            "width": 1080
        },
        "display_url": "https://scontent-ort2-1.cdninstagram.com/vp/0a152089a30f5d630b921e9f53458afd/5AECEEC6/t51.2885-15/e35/25005835_157695618183860_3279920598146351104_n.jpg",
        "edge_media_preview_like": {
            "count": 23
        },
        "edge_media_to_caption": {
            "edges": [
                {
                    "node": {
                        "text": "HR Giger art on @burn_the_church_666 One more session for background. Thanks Shane!"
                    }
                }
            ]
        },
        "edge_media_to_comment": {
            "count": 1
        },
        "id": "1671521800682745397",
        "is_video": false,
        "location": {
            "has_public_page": true,
            "id": "311334",
            "name": "Revolution Tattoo",
            "slug": "revolution-tattoo"
        },
        "owner": {
            "id": "51495250"
        },
        "shortcode": "BcycDi8BC41",
        "tags": [],
        "taken_at_timestamp": 1513480948,
        "thumbnail_resources": [
            {
                "config_height": 150,
                "config_width": 150,
                "src": "https://scontent-ort2-1.cdninstagram.com/vp/b8567073adb59884cbf39f0bad1185e4/5ADFD7A3/t51.2885-15/s150x150/e35/25005835_157695618183860_3279920598146351104_n.jpg"
            },
            {
                "config_height": 240,
                "config_width": 240,
                "src": "https://scontent-ort2-1.cdninstagram.com/vp/671542b8d5bda3efb7e4161888240a2d/5AFA9F9C/t51.2885-15/s240x240/e35/25005835_157695618183860_3279920598146351104_n.jpg"
            },
            {
                "config_height": 320,
                "config_width": 320,
                "src": "https://scontent-ort2-1.cdninstagram.com/vp/1d231748ee60ddaafa486d891b8b650b/5ADA9CE4/t51.2885-15/s320x320/e35/25005835_157695618183860_3279920598146351104_n.jpg"
            },
            {
                "config_height": 480,
                "config_width": 480,
                "src": "https://scontent-ort2-1.cdninstagram.com/vp/8dd8d996a51296ce4fa5d32f1d30b22a/5AF33462/t51.2885-15/s480x480/e35/25005835_157695618183860_3279920598146351104_n.jpg"
            },
            {
                "config_height": 640,
                "config_width": 640,
                "src": "https://scontent-ort2-1.cdninstagram.com/vp/c1b1e12907449c79557d5b868d27e0e3/5AEEBCA7/t51.2885-15/s640x640/sh0.08/e35/25005835_157695618183860_3279920598146351104_n.jpg"
            }
        ],
        "thumbnail_src": "https://scontent-ort2-1.cdninstagram.com/vp/c1b1e12907449c79557d5b868d27e0e3/5AEEBCA7/t51.2885-15/s640x640/sh0.08/e35/25005835_157695618183860_3279920598146351104_n.jpg",
        "urls": [
            "https://scontent-ort2-1.cdninstagram.com/vp/0a152089a30f5d630b921e9f53458afd/5AECEEC6/t51.2885-15/e35/25005835_157695618183860_3279920598146351104_n.jpg"
        ]
    },
    {
        "__typename": "GraphImage",
        "comments_disabled": false,
        "dimensions": {
            "height": 1174,
            "width": 1080
        },
        "display_url": "https://scontent-ort2-1.cdninstagram.com/vp/c34d55859846a02c6fcdc8bbef43623b/5AFF2938/t51.2885-15/e35/24328002_1369102003218332_7331182962915934208_n.jpg",
        "edge_media_preview_like": {
            "count": 57
        },
        "edge_media_to_caption": {
            "edges": [
                {
                    "node": {
                        "text": "Pine tree by @bobbyearly .\n.\n.\n#pine #treetattoo #blackandgrey #christmastree #chicago #chicagotattoo #revolutiontattoo #chicagotattooer #chicagotattooartist #bobbyearly"
                    }
                }
            ]
        },
        "edge_media_to_comment": {
            "count": 0
        },
        "id": "1660494566304169585",
        "is_video": false,
        "location": {
            "has_public_page": true,
            "id": "207925476",
            "name": "Lincoln Park",
            "slug": "lincoln-park"
        },
        "owner": {
            "id": "51495250"
        },
        "shortcode": "BcLQwKoBr5x",
        "tags": [
            "chicagotattooer",
            "chicago",
            "pine",
            "chicagotattooartist",
            "christmastree",
            "treetattoo",
            "blackandgrey",
            "bobbyearly",
            "revolutiontattoo",
            "chicagotattoo"
        ],
        "taken_at_timestamp": 1512166399,
        "thumbnail_resources": [
            {
                "config_height": 150,
                "config_width": 150,
                "src": "https://scontent-ort2-1.cdninstagram.com/vp/34948f042716c97aaf736257c022afad/5AE7B136/t51.2885-15/s150x150/e35/c0.35.814.814/24328002_1369102003218332_7331182962915934208_n.jpg"
            },
            {
                "config_height": 240,
                "config_width": 240,
                "src": "https://scontent-ort2-1.cdninstagram.com/vp/63859b78a06d21c5cda1e909c0b6b8fa/5AD8F5A0/t51.2885-15/s240x240/e35/c0.35.814.814/24328002_1369102003218332_7331182962915934208_n.jpg"
            },
            {
                "config_height": 320,
                "config_width": 320,
                "src": "https://scontent-ort2-1.cdninstagram.com/vp/3668fc313e2d602eef79c8efc069e35c/5ADFA148/t51.2885-15/s320x320/e35/c0.35.814.814/24328002_1369102003218332_7331182962915934208_n.jpg"
            },
            {
                "config_height": 480,
                "config_width": 480,
                "src": "https://scontent-ort2-1.cdninstagram.com/vp/cbaca9462136b88c6fe800094a72d788/5AECA361/t51.2885-15/s480x480/e35/c0.35.814.814/24328002_1369102003218332_7331182962915934208_n.jpg"
            },
            {
                "config_height": 640,
                "config_width": 640,
                "src": "https://scontent-ort2-1.cdninstagram.com/vp/74ff907413601420bae53c5f5b1e65f7/5AE85175/t51.2885-15/s640x640/sh0.08/e35/c0.35.814.814/24328002_1369102003218332_7331182962915934208_n.jpg"
            }
        ],
        "thumbnail_src": "https://scontent-ort2-1.cdninstagram.com/vp/74ff907413601420bae53c5f5b1e65f7/5AE85175/t51.2885-15/s640x640/sh0.08/e35/c0.35.814.814/24328002_1369102003218332_7331182962915934208_n.jpg",
        "urls": [
            "https://scontent-ort2-1.cdninstagram.com/vp/c34d55859846a02c6fcdc8bbef43623b/5AFF2938/t51.2885-15/e35/24328002_1369102003218332_7331182962915934208_n.jpg"
        ]
    },
    {
        "__typename": "GraphImage",
        "comments_disabled": false,
        "dimensions": {
            "height": 1080,
            "width": 1080
        },
        "display_url": "https://scontent-ort2-1.cdninstagram.com/vp/d4af10fc1c3f09f3c099a96777f04cf0/5ADB8D0A/t51.2885-15/e35/23734317_2005934376328504_654607742383685632_n.jpg",
        "edge_media_preview_like": {
            "count": 62
        },
        "edge_media_to_caption": {
            "edges": [
                {
                    "node": {
                        "text": "Nick Cave upper arm by (((oms @witchbanger ... one more session to go on this piece. Color next. #revolutiontattoo #revolutiontattoochicago #nickcave #nickcaveandthebadseeds #chicagotattooshops #tattoosbyoms"
                    }
                }
            ]
        },
        "edge_media_to_comment": {
            "count": 2
        },
        "id": "1654024225469994657",
        "is_video": false,
        "location": {
            "has_public_page": true,
            "id": "255100154",
            "name": "Chicago metropolitan area",
            "slug": "chicago-metropolitan-area"
        },
        "owner": {
            "id": "51495250"
        },
        "shortcode": "Bb0RkUJB5ah",
        "tags": [
            "revolutiontattoochicago",
            "nickcave",
            "tattoosbyoms",
            "chicagotattooshops",
            "revolutiontattoo",
            "nickcaveandthebadseeds"
        ],
        "taken_at_timestamp": 1511395074,
        "thumbnail_resources": [
            {
                "config_height": 150,
                "config_width": 150,
                "src": "https://scontent-ort2-1.cdninstagram.com/vp/00cf3dac4c7fd0a0862bcfa3856baa5b/5AFEA76F/t51.2885-15/s150x150/e35/23734317_2005934376328504_654607742383685632_n.jpg"
            },
            {
                "config_height": 240,
                "config_width": 240,
                "src": "https://scontent-ort2-1.cdninstagram.com/vp/d83c336c0f151a4374d101989408d3a1/5AECD350/t51.2885-15/s240x240/e35/23734317_2005934376328504_654607742383685632_n.jpg"
            },
            {
                "config_height": 320,
                "config_width": 320,
                "src": "https://scontent-ort2-1.cdninstagram.com/vp/fe90825095e0af04749f938a5e7d7ffc/5AF16A28/t51.2885-15/s320x320/e35/23734317_2005934376328504_654607742383685632_n.jpg"
            },
            {
                "config_height": 480,
                "config_width": 480,
                "src": "https://scontent-ort2-1.cdninstagram.com/vp/18d2ddac7c5ecbcea0d903a6450f30d1/5AE143AE/t51.2885-15/s480x480/e35/23734317_2005934376328504_654607742383685632_n.jpg"
            },
            {
                "config_height": 640,
                "config_width": 640,
                "src": "https://scontent-ort2-1.cdninstagram.com/vp/660d16ba49c99addbfb9783a72992800/5AFC686B/t51.2885-15/s640x640/sh0.08/e35/23734317_2005934376328504_654607742383685632_n.jpg"
            }
        ],
        "thumbnail_src": "https://scontent-ort2-1.cdninstagram.com/vp/660d16ba49c99addbfb9783a72992800/5AFC686B/t51.2885-15/s640x640/sh0.08/e35/23734317_2005934376328504_654607742383685632_n.jpg",
        "urls": [
            "https://scontent-ort2-1.cdninstagram.com/vp/d4af10fc1c3f09f3c099a96777f04cf0/5ADB8D0A/t51.2885-15/e35/23734317_2005934376328504_654607742383685632_n.jpg"
        ]
    },
    {
        "__typename": "GraphImage",
        "comments_disabled": false,
        "dimensions": {
            "height": 1344,
            "width": 1080
        },
        "display_url": "https://scontent-ort2-1.cdninstagram.com/vp/a01201954d39a8d892ee0b211fbd52da/5AE46C2C/t51.2885-15/e35/23595907_877763162390348_5926671963555627008_n.jpg",
        "edge_media_preview_like": {
            "count": 44
        },
        "edge_media_to_caption": {
            "edges": [
                {
                    "node": {
                        "text": "Flower child by @kyleadani  #flowerchild #hippy #neotraditional #chicago #chicagotattooshops"
                    }
                }
            ]
        },
        "edge_media_to_comment": {
            "count": 1
        },
        "id": "1651170869994879891",
        "is_video": false,
        "location": null,
        "owner": {
            "id": "51495250"
        },
        "shortcode": "BbqIyhxhHuT",
        "tags": [
            "flowerchild",
            "chicago",
            "hippy",
            "neotraditional",
            "chicagotattooshops"
        ],
        "taken_at_timestamp": 1511054928,
        "thumbnail_resources": [
            {
                "config_height": 150,
                "config_width": 150,
                "src": "https://scontent-ort2-1.cdninstagram.com/vp/2ce3d2aebdcc7b62eb3494419d982c74/5ADC36C2/t51.2885-15/s150x150/e35/c0.132.1080.1080/23595907_877763162390348_5926671963555627008_n.jpg"
            },
            {
                "config_height": 240,
                "config_width": 240,
                "src": "https://scontent-ort2-1.cdninstagram.com/vp/228501d26cd29a69a4b9e5250f3468fc/5ADCDFA9/t51.2885-15/s240x240/e35/c0.132.1080.1080/23595907_877763162390348_5926671963555627008_n.jpg"
            },
            {
                "config_height": 320,
                "config_width": 320,
                "src": "https://scontent-ort2-1.cdninstagram.com/vp/b1240b82ccd421431a9227c88b6b8e2d/5AFABE61/t51.2885-15/s320x320/e35/c0.132.1080.1080/23595907_877763162390348_5926671963555627008_n.jpg"
            },
            {
                "config_height": 480,
                "config_width": 480,
                "src": "https://scontent-ort2-1.cdninstagram.com/vp/555966ea5f0c6f5f47ca1ba14de32acc/5AE8578B/t51.2885-15/s480x480/e35/c0.132.1080.1080/23595907_877763162390348_5926671963555627008_n.jpg"
            },
            {
                "config_height": 640,
                "config_width": 640,
                "src": "https://scontent-ort2-1.cdninstagram.com/vp/03fc50744da83cb5208edca572412a3c/5AF2292C/t51.2885-15/s640x640/sh0.08/e35/c0.132.1080.1080/23595907_877763162390348_5926671963555627008_n.jpg"
            }
        ],
        "thumbnail_src": "https://scontent-ort2-1.cdninstagram.com/vp/03fc50744da83cb5208edca572412a3c/5AF2292C/t51.2885-15/s640x640/sh0.08/e35/c0.132.1080.1080/23595907_877763162390348_5926671963555627008_n.jpg",
        "urls": [
            "https://scontent-ort2-1.cdninstagram.com/vp/a01201954d39a8d892ee0b211fbd52da/5AE46C2C/t51.2885-15/e35/23595907_877763162390348_5926671963555627008_n.jpg"
        ]
    },
    {
        "__typename": "GraphImage",
        "comments_disabled": false,
        "dimensions": {
            "height": 815,
            "width": 1080
        },
        "display_url": "https://scontent-ort2-1.cdninstagram.com/vp/491d3f371a2c6e6d25aeec61a0be361e/5AFBF35B/t51.2885-15/e35/23734037_298694743954884_1508027802912292864_n.jpg",
        "edge_media_preview_like": {
            "count": 40
        },
        "edge_media_to_caption": {
            "edges": [
                {
                    "node": {
                        "text": "Flash sheet by @kyleadani  #traditionaltattoo #tattooflash #chicago #chicagotattooshops"
                    }
                }
            ]
        },
        "edge_media_to_comment": {
            "count": 0
        },
        "id": "1651170014507841433",
        "is_video": false,
        "location": null,
        "owner": {
            "id": "51495250"
        },
        "shortcode": "BbqImFChDeZ",
        "tags": [
            "chicagotattooshops",
            "traditionaltattoo",
            "tattooflash",
            "chicago"
        ],
        "taken_at_timestamp": 1511054826,
        "thumbnail_resources": [
            {
                "config_height": 150,
                "config_width": 150,
                "src": "https://scontent-ort2-1.cdninstagram.com/vp/fe0b91c036bdc7103d739e3e44fa223d/5AE9F933/t51.2885-15/s150x150/e35/c132.0.815.815/23734037_298694743954884_1508027802912292864_n.jpg"
            },
            {
                "config_height": 240,
                "config_width": 240,
                "src": "https://scontent-ort2-1.cdninstagram.com/vp/f6d6940be412b4eaba6ca8aebe0ffade/5AFCC5A5/t51.2885-15/s240x240/e35/c132.0.815.815/23734037_298694743954884_1508027802912292864_n.jpg"
            },
            {
                "config_height": 320,
                "config_width": 320,
                "src": "https://scontent-ort2-1.cdninstagram.com/vp/069d2b22a93db288f19da378e1fe6085/5AF2984D/t51.2885-15/s320x320/e35/c132.0.815.815/23734037_298694743954884_1508027802912292864_n.jpg"
            },
            {
                "config_height": 480,
                "config_width": 480,
                "src": "https://scontent-ort2-1.cdninstagram.com/vp/1384ff0c0756f8c9ebc4fe730f442db7/5AFE5F64/t51.2885-15/s480x480/e35/c132.0.815.815/23734037_298694743954884_1508027802912292864_n.jpg"
            },
            {
                "config_height": 640,
                "config_width": 640,
                "src": "https://scontent-ort2-1.cdninstagram.com/vp/9d5245ff320cffa883d6dff236f29d3c/5AE29270/t51.2885-15/s640x640/sh0.08/e35/c132.0.815.815/23734037_298694743954884_1508027802912292864_n.jpg"
            }
        ],
        "thumbnail_src": "https://scontent-ort2-1.cdninstagram.com/vp/9d5245ff320cffa883d6dff236f29d3c/5AE29270/t51.2885-15/s640x640/sh0.08/e35/c132.0.815.815/23734037_298694743954884_1508027802912292864_n.jpg",
        "urls": [
            "https://scontent-ort2-1.cdninstagram.com/vp/491d3f371a2c6e6d25aeec61a0be361e/5AFBF35B/t51.2885-15/e35/23734037_298694743954884_1508027802912292864_n.jpg"
        ]
    },
    {
        "__typename": "GraphVideo",
        "comments_disabled": false,
        "dimensions": {
            "height": 750,
            "width": 750
        },
        "display_url": "https://scontent-ort2-1.cdninstagram.com/vp/60e160928109140992c84bcd1983ad64/5A633F83/t51.2885-15/e15/23498396_523046411362345_1247861322893230080_n.jpg",
        "edge_media_preview_like": {
            "count": 46
        },
        "edge_media_to_caption": {
            "edges": [
                {
                    "node": {
                        "text": "Rose by @kyleadani  #rose #traditionaltattoo #tradtattoo #chicago #chicagotattooshops"
                    }
                }
            ]
        },
        "edge_media_to_comment": {
            "count": 0
        },
        "id": "1646142561796328274",
        "is_video": true,
        "location": null,
        "owner": {
            "id": "51495250"
        },
        "shortcode": "BbYRfA1hYtS",
        "tags": [
            "chicago",
            "tradtattoo",
            "traditionaltattoo",
            "chicagotattooshops",
            "rose"
        ],
        "taken_at_timestamp": 1510455507,
        "thumbnail_resources": [
            {
                "config_height": 150,
                "config_width": 150,
                "src": "https://scontent-ort2-1.cdninstagram.com/vp/46cf95b1874909b2de28dfe9abd4d205/5A636DE6/t51.2885-15/s150x150/e15/23498396_523046411362345_1247861322893230080_n.jpg"
            },
            {
                "config_height": 240,
                "config_width": 240,
                "src": "https://scontent-ort2-1.cdninstagram.com/vp/f4b916d12c5bc2e7b07632ea5e09b16d/5A63B799/t51.2885-15/s240x240/e15/23498396_523046411362345_1247861322893230080_n.jpg"
            },
            {
                "config_height": 320,
                "config_width": 320,
                "src": "https://scontent-ort2-1.cdninstagram.com/vp/dcf10c93925525426f3c84c66321fb5a/5A6369A1/t51.2885-15/s320x320/e15/23498396_523046411362345_1247861322893230080_n.jpg"
            },
            {
                "config_height": 480,
                "config_width": 480,
                "src": "https://scontent-ort2-1.cdninstagram.com/vp/95d8015abcede5e88a8d21078cacecdf/5A638327/t51.2885-15/s480x480/e15/23498396_523046411362345_1247861322893230080_n.jpg"
            },
            {
                "config_height": 640,
                "config_width": 640,
                "src": "https://scontent-ort2-1.cdninstagram.com/vp/0dbd8e41d477db3b5c33d9188af40146/5A635D17/t51.2885-15/s640x640/e15/23498396_523046411362345_1247861322893230080_n.jpg"
            }
        ],
        "thumbnail_src": "https://scontent-ort2-1.cdninstagram.com/vp/0dbd8e41d477db3b5c33d9188af40146/5A635D17/t51.2885-15/s640x640/e15/23498396_523046411362345_1247861322893230080_n.jpg",
        "urls": [
            "https://scontent-ort2-1.cdninstagram.com/vp/c68b9595a944fda6120d457272307cf5/5A63A765/t50.2886-16/23537090_1256639121103330_2431844073934422016_n.mp4"
        ],
        "video_view_count": 0
    },
    {
        "__typename": "GraphImage",
        "comments_disabled": false,
        "dimensions": {
            "height": 1350,
            "width": 1080
        },
        "display_url": "https://scontent-ort2-1.cdninstagram.com/vp/51d792147339085e54c24dd5a3b21035/5AF371BF/t51.2885-15/e35/23421314_500995546936140_3043569363891257344_n.jpg",
        "edge_media_preview_like": {
            "count": 131
        },
        "edge_media_to_caption": {
            "edges": [
                {
                    "node": {
                        "text": "Butterfly by @kyleadani  #butterfly #traditionaltattoo #tradtattoo #chicago #chicagotattooshops"
                    }
                }
            ]
        },
        "edge_media_to_comment": {
            "count": 0
        },
        "id": "1646141071375576710",
        "is_video": false,
        "location": null,
        "owner": {
            "id": "51495250"
        },
        "shortcode": "BbYRJUxha6G",
        "tags": [
            "chicago",
            "tradtattoo",
            "butterfly",
            "traditionaltattoo",
            "chicagotattooshops"
        ],
        "taken_at_timestamp": 1510455329,
        "thumbnail_resources": [
            {
                "config_height": 150,
                "config_width": 150,
                "src": "https://scontent-ort2-1.cdninstagram.com/vp/0ab609645ac1ba1a16ac96fac229fa87/5AE97383/t51.2885-15/s150x150/e35/c0.135.1080.1080/23421314_500995546936140_3043569363891257344_n.jpg"
            },
            {
                "config_height": 240,
                "config_width": 240,
                "src": "https://scontent-ort2-1.cdninstagram.com/vp/c29719488dfe514f45b9d19d1e5732ae/5AE0ECE8/t51.2885-15/s240x240/e35/c0.135.1080.1080/23421314_500995546936140_3043569363891257344_n.jpg"
            },
            {
                "config_height": 320,
                "config_width": 320,
                "src": "https://scontent-ort2-1.cdninstagram.com/vp/72d551ec21a0776287ebe97c2c25fb25/5ADBB020/t51.2885-15/s320x320/e35/c0.135.1080.1080/23421314_500995546936140_3043569363891257344_n.jpg"
            },
            {
                "config_height": 480,
                "config_width": 480,
                "src": "https://scontent-ort2-1.cdninstagram.com/vp/34f4febc29c1faa14da729eacff33074/5AE8DCCA/t51.2885-15/s480x480/e35/c0.135.1080.1080/23421314_500995546936140_3043569363891257344_n.jpg"
            },
            {
                "config_height": 640,
                "config_width": 640,
                "src": "https://scontent-ort2-1.cdninstagram.com/vp/95e312c43047538ba643736fcdffb506/5AF24D6D/t51.2885-15/s640x640/sh0.08/e35/c0.135.1080.1080/23421314_500995546936140_3043569363891257344_n.jpg"
            }
        ],
        "thumbnail_src": "https://scontent-ort2-1.cdninstagram.com/vp/95e312c43047538ba643736fcdffb506/5AF24D6D/t51.2885-15/s640x640/sh0.08/e35/c0.135.1080.1080/23421314_500995546936140_3043569363891257344_n.jpg",
        "urls": [
            "https://scontent-ort2-1.cdninstagram.com/vp/51d792147339085e54c24dd5a3b21035/5AF371BF/t51.2885-15/e35/23421314_500995546936140_3043569363891257344_n.jpg"
        ]
    },
    {
        "__typename": "GraphImage",
        "comments_disabled": false,
        "dimensions": {
            "height": 1350,
            "width": 1080
        },
        "display_url": "https://scontent-ort2-1.cdninstagram.com/vp/9775f1926370755ed50032b0109a48d6/5AF112BB/t51.2885-15/e35/23416384_153370678606223_7115564059784642560_n.jpg",
        "edge_media_preview_like": {
            "count": 44
        },
        "edge_media_to_caption": {
            "edges": [
                {
                    "node": {
                        "text": "Victorian lady, by @kyleadani  #victorian #ladyhead #traditionaltattoo #tradtattoo #chicago #chicagotattooshop"
                    }
                }
            ]
        },
        "edge_media_to_comment": {
            "count": 0
        },
        "id": "1646140251305357660",
        "is_video": false,
        "location": null,
        "owner": {
            "id": "51495250"
        },
        "shortcode": "BbYQ9ZBhzFc",
        "tags": [
            "chicago",
            "victorian",
            "tradtattoo",
            "ladyhead",
            "traditionaltattoo",
            "chicagotattooshop"
        ],
        "taken_at_timestamp": 1510455231,
        "thumbnail_resources": [
            {
                "config_height": 150,
                "config_width": 150,
                "src": "https://scontent-ort2-1.cdninstagram.com/vp/a87bb38bd630f28ebeb68ba5eb3b8c51/5AE66187/t51.2885-15/s150x150/e35/c0.135.1080.1080/23416384_153370678606223_7115564059784642560_n.jpg"
            },
            {
                "config_height": 240,
                "config_width": 240,
                "src": "https://scontent-ort2-1.cdninstagram.com/vp/882c6f344ba3b0013af9991874339f1b/5AEFD5EC/t51.2885-15/s240x240/e35/c0.135.1080.1080/23416384_153370678606223_7115564059784642560_n.jpg"
            },
            {
                "config_height": 320,
                "config_width": 320,
                "src": "https://scontent-ort2-1.cdninstagram.com/vp/03c3d4ee9d949315bce0be40c31d156b/5AE50324/t51.2885-15/s320x320/e35/c0.135.1080.1080/23416384_153370678606223_7115564059784642560_n.jpg"
            },
            {
                "config_height": 480,
                "config_width": 480,
                "src": "https://scontent-ort2-1.cdninstagram.com/vp/c5bb7526e68d430504e4e1fa686cbfe5/5AF1AFCE/t51.2885-15/s480x480/e35/c0.135.1080.1080/23416384_153370678606223_7115564059784642560_n.jpg"
            },
            {
                "config_height": 640,
                "config_width": 640,
                "src": "https://scontent-ort2-1.cdninstagram.com/vp/7bc52628dc26922fe45e40c5a549e2a2/5AEB6469/t51.2885-15/s640x640/sh0.08/e35/c0.135.1080.1080/23416384_153370678606223_7115564059784642560_n.jpg"
            }
        ],
        "thumbnail_src": "https://scontent-ort2-1.cdninstagram.com/vp/7bc52628dc26922fe45e40c5a549e2a2/5AEB6469/t51.2885-15/s640x640/sh0.08/e35/c0.135.1080.1080/23416384_153370678606223_7115564059784642560_n.jpg",
        "urls": [
            "https://scontent-ort2-1.cdninstagram.com/vp/9775f1926370755ed50032b0109a48d6/5AF112BB/t51.2885-15/e35/23416384_153370678606223_7115564059784642560_n.jpg"
        ]
    },
    {
        "__typename": "GraphImage",
        "comments_disabled": false,
        "dimensions": {
            "height": 750,
            "width": 750
        },
        "display_url": "https://scontent-ort2-1.cdninstagram.com/vp/24979eb76527dc25017de5754096afc9/5AE86E2E/t51.2885-15/e35/23416378_1677615868923314_384130136808620032_n.jpg",
        "edge_media_preview_like": {
            "count": 35
        },
        "edge_media_to_caption": {
            "edges": [
                {
                    "node": {
                        "text": "By @bobbyearly\n.\n.\n.\n#blackandgrey #abstract #portrait #illustrativetattoo #portraittattoo #chicago #chicagotattoo #revolutiontattoo #chicagotattooer #chicagotattooartist #bobbyearly"
                    }
                }
            ]
        },
        "edge_media_to_comment": {
            "count": 0
        },
        "id": "1646029379090058829",
        "is_video": false,
        "location": {
            "has_public_page": true,
            "id": "726351604241773",
            "name": "Revolution Studios",
            "slug": "revolution-studios"
        },
        "owner": {
            "id": "51495250"
        },
        "shortcode": "BbX3v_OhQ5N",
        "tags": [
            "chicagotattooer",
            "chicago",
            "chicagotattooartist",
            "illustrativetattoo",
            "abstract",
            "portraittattoo",
            "blackandgrey",
            "bobbyearly",
            "portrait",
            "revolutiontattoo",
            "chicagotattoo"
        ],
        "taken_at_timestamp": 1510442014,
        "thumbnail_resources": [
            {
                "config_height": 150,
                "config_width": 150,
                "src": "https://scontent-ort2-1.cdninstagram.com/vp/bc8c1ae2819987f17edfe9e3495977dc/5AF7D64B/t51.2885-15/s150x150/e35/23416378_1677615868923314_384130136808620032_n.jpg"
            },
            {
                "config_height": 240,
                "config_width": 240,
                "src": "https://scontent-ort2-1.cdninstagram.com/vp/5ce063b2a46e96539843c528bd65dc99/5AF0EA74/t51.2885-15/s240x240/e35/23416378_1677615868923314_384130136808620032_n.jpg"
            },
            {
                "config_height": 320,
                "config_width": 320,
                "src": "https://scontent-ort2-1.cdninstagram.com/vp/3f29f0b0abd7425d9e362d44a0559a82/5AEB9D0C/t51.2885-15/s320x320/e35/23416378_1677615868923314_384130136808620032_n.jpg"
            },
            {
                "config_height": 480,
                "config_width": 480,
                "src": "https://scontent-ort2-1.cdninstagram.com/vp/89585c48d7697932b1bf5bd9ee8cf874/5AF7F68A/t51.2885-15/s480x480/e35/23416378_1677615868923314_384130136808620032_n.jpg"
            },
            {
                "config_height": 640,
                "config_width": 640,
                "src": "https://scontent-ort2-1.cdninstagram.com/vp/861f263a9ca8dcc57002dfd576c208b1/5AE6454F/t51.2885-15/s640x640/sh0.08/e35/23416378_1677615868923314_384130136808620032_n.jpg"
            }
        ],
        "thumbnail_src": "https://scontent-ort2-1.cdninstagram.com/vp/861f263a9ca8dcc57002dfd576c208b1/5AE6454F/t51.2885-15/s640x640/sh0.08/e35/23416378_1677615868923314_384130136808620032_n.jpg",
        "urls": [
            "https://scontent-ort2-1.cdninstagram.com/vp/24979eb76527dc25017de5754096afc9/5AE86E2E/t51.2885-15/e35/23416378_1677615868923314_384130136808620032_n.jpg"
        ]
    },
    {
        "__typename": "GraphSidecar",
        "comments_disabled": false,
        "dimensions": {
            "height": 1080,
            "width": 1080
        },
        "display_url": "https://scontent-ort2-1.cdninstagram.com/vp/45aeb56996ae5157907e3a1856cc3085/5ADA98AD/t51.2885-15/e35/23498478_142418373149491_6617801818606927872_n.jpg",
        "edge_media_preview_like": {
            "count": 89
        },
        "edge_media_to_caption": {
            "edges": [
                {
                    "node": {
                        "text": "Thank you @nicolascainlife for doing some killer tattoos at the shop.  Safe travels and see you soon. ❤ #travelingartist #freespirit #blackandgreytattoo #skulltattoo #drippyskull #chicagotattooshops #revolutiontattoochicago"
                    }
                }
            ]
        },
        "edge_media_to_comment": {
            "count": 1
        },
        "id": "1644770259867297530",
        "is_video": false,
        "location": {
            "has_public_page": true,
            "id": "204517928",
            "name": "Chicago, Illinois",
            "slug": "chicago-illinois"
        },
        "owner": {
            "id": "51495250"
        },
        "shortcode": "BbTZdZEhGb6",
        "tags": [
            "revolutiontattoochicago",
            "freespirit",
            "skulltattoo",
            "travelingartist",
            "drippyskull",
            "blackandgreytattoo",
            "chicagotattooshops"
        ],
        "taken_at_timestamp": 1510291915,
        "thumbnail_resources": [
            {
                "config_height": 150,
                "config_width": 150,
                "src": "https://scontent-ort2-1.cdninstagram.com/vp/0171c33be155a205111ba13c570f38ad/5AE2B7C8/t51.2885-15/s150x150/e35/23498478_142418373149491_6617801818606927872_n.jpg"
            },
            {
                "config_height": 240,
                "config_width": 240,
                "src": "https://scontent-ort2-1.cdninstagram.com/vp/bcf736ec4ad4b0aa15f7dcd13abd9fd6/5AFD89F7/t51.2885-15/s240x240/e35/23498478_142418373149491_6617801818606927872_n.jpg"
            },
            {
                "config_height": 320,
                "config_width": 320,
                "src": "https://scontent-ort2-1.cdninstagram.com/vp/40185ab4d9075e5124e461e3f06bad48/5AFD398F/t51.2885-15/s320x320/e35/23498478_142418373149491_6617801818606927872_n.jpg"
            },
            {
                "config_height": 480,
                "config_width": 480,
                "src": "https://scontent-ort2-1.cdninstagram.com/vp/0dcd6eaf1b6b28dd775451c5798f75d7/5AEAFC09/t51.2885-15/s480x480/e35/23498478_142418373149491_6617801818606927872_n.jpg"
            },
            {
                "config_height": 640,
                "config_width": 640,
                "src": "https://scontent-ort2-1.cdninstagram.com/vp/733e373fd9088d1ad1884cca27acceac/5AE91CCC/t51.2885-15/s640x640/sh0.08/e35/23498478_142418373149491_6617801818606927872_n.jpg"
            }
        ],
        "thumbnail_src": "https://scontent-ort2-1.cdninstagram.com/vp/733e373fd9088d1ad1884cca27acceac/5AE91CCC/t51.2885-15/s640x640/sh0.08/e35/23498478_142418373149491_6617801818606927872_n.jpg",
        "urls": [
            "https://scontent-ort2-1.cdninstagram.com/vp/45aeb56996ae5157907e3a1856cc3085/5ADA98AD/t51.2885-15/e35/23498478_142418373149491_6617801818606927872_n.jpg",
            "https://scontent-ort2-1.cdninstagram.com/vp/77413940500ba89cd675a5c24466469e/5AF1EF0C/t51.2885-15/e35/23416942_128475594508578_5759824763417526272_n.jpg",
            "https://scontent-ort2-1.cdninstagram.com/vp/7e5a7b8bb248aa89de9ae46816b6f3e6/5AE0A15D/t51.2885-15/e35/23422008_371300636652145_3500620606502600704_n.jpg"
        ]
    },
    {
        "__typename": "GraphImage",
        "comments_disabled": false,
        "dimensions": {
            "height": 1080,
            "width": 1080
        },
        "display_url": "https://scontent-ort2-1.cdninstagram.com/vp/5663a06b52afd93e235fad3ab075a900/5AE5ECAD/t51.2885-15/e35/23348237_1913140565368559_8561128126086643712_n.jpg",
        "edge_media_preview_like": {
            "count": 43
        },
        "edge_media_to_caption": {
            "edges": [
                {
                    "node": {
                        "text": "@bobbyearly in action working on a time lapse video of a Nas portrait #chicagotattooartist #chicagotattooshops #portraittattoo #revolutiontattoochicago #nas #nastattoo"
                    }
                }
            ]
        },
        "edge_media_to_comment": {
            "count": 2
        },
        "id": "1644668775419067748",
        "is_video": false,
        "location": {
            "has_public_page": true,
            "id": "204517928",
            "name": "Chicago, Illinois",
            "slug": "chicago-illinois"
        },
        "owner": {
            "id": "51495250"
        },
        "shortcode": "BbTCYmUB71k",
        "tags": [
            "revolutiontattoochicago",
            "chicagotattooartist",
            "nastattoo",
            "nas",
            "portraittattoo",
            "chicagotattooshops"
        ],
        "taken_at_timestamp": 1510279817,
        "thumbnail_resources": [
            {
                "config_height": 150,
                "config_width": 150,
                "src": "https://scontent-ort2-1.cdninstagram.com/vp/963fe90106376fdcc7901b1fe4abd777/5AEC06FA/t51.2885-15/s150x150/e35/23348237_1913140565368559_8561128126086643712_n.jpg"
            },
            {
                "config_height": 240,
                "config_width": 240,
                "src": "https://scontent-ort2-1.cdninstagram.com/vp/3589422df037a4a850caa28228eba02a/5AE2406E/t51.2885-15/s240x240/e35/23348237_1913140565368559_8561128126086643712_n.jpg"
            },
            {
                "config_height": 320,
                "config_width": 320,
                "src": "https://scontent-ort2-1.cdninstagram.com/vp/8c11cbe682baf1fbe1b160296608e959/5AF3DACA/t51.2885-15/s320x320/e35/23348237_1913140565368559_8561128126086643712_n.jpg"
            },
            {
                "config_height": 480,
                "config_width": 480,
                "src": "https://scontent-ort2-1.cdninstagram.com/vp/eef695393e1c85db2272e39e3ba2bd58/5AE49A92/t51.2885-15/s480x480/e35/23348237_1913140565368559_8561128126086643712_n.jpg"
            },
            {
                "config_height": 640,
                "config_width": 640,
                "src": "https://scontent-ort2-1.cdninstagram.com/vp/3d74be955ab0d8c25b2b8caa41ba30bc/5AFC1D87/t51.2885-15/s640x640/sh0.08/e35/23348237_1913140565368559_8561128126086643712_n.jpg"
            }
        ],
        "thumbnail_src": "https://scontent-ort2-1.cdninstagram.com/vp/3d74be955ab0d8c25b2b8caa41ba30bc/5AFC1D87/t51.2885-15/s640x640/sh0.08/e35/23348237_1913140565368559_8561128126086643712_n.jpg",
        "urls": [
            "https://scontent-ort2-1.cdninstagram.com/vp/5663a06b52afd93e235fad3ab075a900/5AE5ECAD/t51.2885-15/e35/23348237_1913140565368559_8561128126086643712_n.jpg"
        ]
    },
    {
        "__typename": "GraphSidecar",
        "comments_disabled": false,
        "dimensions": {
            "height": 640,
            "width": 640
        },
        "display_url": "https://scontent-ort2-1.cdninstagram.com/vp/264ba91fe964077cf9c1a4878eb7c40f/5ADEEF8A/t51.2885-15/e35/23164013_128782054466100_9010662591814434816_n.jpg",
        "edge_media_preview_like": {
            "count": 46
        },
        "edge_media_to_caption": {
            "edges": [
                {
                    "node": {
                        "text": "Pet portraits!!! Done by (((oms @witchbanger #revolutiontattoo  #revolutiontattoochicago #chicagotattooshops #chicagotattooartist #petportrait #memorialtattoo #tattoosbyoms"
                    }
                }
            ]
        },
        "edge_media_to_comment": {
            "count": 0
        },
        "id": "1641174361052767148",
        "is_video": false,
        "location": {
            "has_public_page": true,
            "id": "298741817",
            "name": "PAWS Chicago - Adoption Centers",
            "slug": "paws-chicago-adoption-centers"
        },
        "owner": {
            "id": "51495250"
        },
        "shortcode": "BbGn2LVB2Os",
        "tags": [
            "revolutiontattoochicago",
            "chicagotattooartist",
            "petportrait",
            "tattoosbyoms",
            "memorialtattoo",
            "chicagotattooshops",
            "revolutiontattoo"
        ],
        "taken_at_timestamp": 1509863251,
        "thumbnail_resources": [
            {
                "config_height": 150,
                "config_width": 150,
                "src": "https://scontent-ort2-1.cdninstagram.com/vp/a5bf0d0e77e5d1386f20313b7d4e88c5/5ADA63EF/t51.2885-15/s150x150/e35/23164013_128782054466100_9010662591814434816_n.jpg"
            },
            {
                "config_height": 240,
                "config_width": 240,
                "src": "https://scontent-ort2-1.cdninstagram.com/vp/e9567373f8c4a49f3b334978ca0c74d3/5AEA91D0/t51.2885-15/s240x240/e35/23164013_128782054466100_9010662591814434816_n.jpg"
            },
            {
                "config_height": 320,
                "config_width": 320,
                "src": "https://scontent-ort2-1.cdninstagram.com/vp/475536b0722cdd4b258f48a5dac6790c/5AEBA5A8/t51.2885-15/s320x320/e35/23164013_128782054466100_9010662591814434816_n.jpg"
            },
            {
                "config_height": 480,
                "config_width": 480,
                "src": "https://scontent-ort2-1.cdninstagram.com/vp/ea9e7ca01c1ea35e1512c3689fff7f2c/5AE4002E/t51.2885-15/s480x480/e35/23164013_128782054466100_9010662591814434816_n.jpg"
            },
            {
                "config_height": 640,
                "config_width": 640,
                "src": "https://scontent-ort2-1.cdninstagram.com/vp/264ba91fe964077cf9c1a4878eb7c40f/5ADEEF8A/t51.2885-15/e35/23164013_128782054466100_9010662591814434816_n.jpg"
            }
        ],
        "thumbnail_src": "https://scontent-ort2-1.cdninstagram.com/vp/264ba91fe964077cf9c1a4878eb7c40f/5ADEEF8A/t51.2885-15/e35/23164013_128782054466100_9010662591814434816_n.jpg",
        "urls": [
            "https://scontent-ort2-1.cdninstagram.com/vp/264ba91fe964077cf9c1a4878eb7c40f/5ADEEF8A/t51.2885-15/e35/23164013_128782054466100_9010662591814434816_n.jpg",
            "https://scontent-ort2-1.cdninstagram.com/vp/895bdd45fa19b9b49edf68a34449ccf4/5AF602D0/t51.2885-15/e35/23347722_375946179508727_6009087060206419968_n.jpg",
            "https://scontent-ort2-1.cdninstagram.com/vp/83b0d80cc8c79cf71e2bddf521506272/5AFBBAC6/t51.2885-15/e35/23161564_554713281559198_9212566650757316608_n.jpg"
        ]
    }
]